llama_index/core/__init__.py
llama_index/core/async_utils.py
llama_index/core/constants.py
llama_index/core/image_retriever.py
llama_index/core/img_utils.py
llama_index/core/py.typed
llama_index/core/schema.py
llama_index/core/service_context.py
llama_index/core/settings.py
llama_index/core/types.py
llama_index/core/utils.py
llama_index/core/_static/.gitignore
llama_index/core/_static/nltk_cache/.gitignore
llama_index/core/_static/nltk_cache/corpora/stopwords/README
llama_index/core/_static/nltk_cache/corpora/stopwords/albanian
llama_index/core/_static/nltk_cache/corpora/stopwords/arabic
llama_index/core/_static/nltk_cache/corpora/stopwords/azerbaijani
llama_index/core/_static/nltk_cache/corpora/stopwords/basque
llama_index/core/_static/nltk_cache/corpora/stopwords/belarusian
llama_index/core/_static/nltk_cache/corpora/stopwords/bengali
llama_index/core/_static/nltk_cache/corpora/stopwords/catalan
llama_index/core/_static/nltk_cache/corpora/stopwords/chinese
llama_index/core/_static/nltk_cache/corpora/stopwords/danish
llama_index/core/_static/nltk_cache/corpora/stopwords/dutch
llama_index/core/_static/nltk_cache/corpora/stopwords/english
llama_index/core/_static/nltk_cache/corpora/stopwords/finnish
llama_index/core/_static/nltk_cache/corpora/stopwords/french
llama_index/core/_static/nltk_cache/corpora/stopwords/german
llama_index/core/_static/nltk_cache/corpora/stopwords/greek
llama_index/core/_static/nltk_cache/corpora/stopwords/hebrew
llama_index/core/_static/nltk_cache/corpora/stopwords/hinglish
llama_index/core/_static/nltk_cache/corpora/stopwords/hungarian
llama_index/core/_static/nltk_cache/corpora/stopwords/indonesian
llama_index/core/_static/nltk_cache/corpora/stopwords/italian
llama_index/core/_static/nltk_cache/corpora/stopwords/kazakh
llama_index/core/_static/nltk_cache/corpora/stopwords/nepali
llama_index/core/_static/nltk_cache/corpora/stopwords/norwegian
llama_index/core/_static/nltk_cache/corpora/stopwords/portuguese
llama_index_core-0.14.0.dist-info/METADATA
llama_index_core-0.14.0.dist-info/WHEEL
llama_index_core-0.14.0.dist-info/licenses/LICENSE
llama_index_core-0.14.0.dist-info/RECORD
